pyppe/__init__.py
pyppe/helloworld.py
pyppe-0.0.1.dist-info/LICENSE
pyppe-0.0.1.dist-info/METADATA
pyppe-0.0.1.dist-info/WHEEL
pyppe-0.0.1.dist-info/top_level.txt
pyppe-0.0.1.dist-info/RECORD
