Metadata-Version: 2.1
Name: pyppe
Version: 0.0.1
Summary: A modular data pipeline for Python
Home-page: https://github.com/RickySal/Pyppe
Author: RickySal
Author-email: 41027013+RickySal@users.noreply.github.com
License: GNU General Public License v3.0
License-File: LICENSE
